{
    "posts":[

        {
            title:POst1,
            date: "junho 8 2022",
            autor:"Rodolfo silva",
            image:"www.placeholder.com",
            category:"category1"
        },
        {
            "title":"POst2",
            "date": "junho 8 2022",
            "autor":"Rodolfo silva",
            "image":"www.placeholder.com",
            "category":"category2"
        },
        {
            "title":"POst3",
            "date": "junho 8 2022",
            "autor":"Rodolfo silva",
            "image":"www.placeholder.com",
            "category":"category3"
        },
        {
            "title":"POst",
            "date": "junho 8 2022",
            "autor":"Rodolfo silva",
            "image":"www.placeholder.com",
            "category":"category4"
        }
    ]
}